{
  "version": 1,
  "skills": {
    "auto-updater": {
      "source": "teylersf/openclaw-auto-updater",
      "sourceType": "github",
      "skillPath": "SKILL.md",
      "computedHash": "c26d504acbd98c6f34506b4e68a0e864d066516354b27c06f72e33c9fce65d1e"
    },
    "frontend-design": {
      "source": "anthropics/skills",
      "sourceType": "github",
      "skillPath": "skills/frontend-design/SKILL.md",
      "computedHash": "93f53fd1c0352d3d7ec17b8f73d7351bf76f4821e55d123c9d2abc2c53ba48e4"
    }
  }
}
